<?xml version="1.0" encoding="UTF-8"?>

<document>
  <segment instanceid="a_book_of_natural_history_35.txt_1" begin="61" end="69">
    <text>breeding</text>
    <mainVerb begin="61" end="69">breeding</mainVerb>
    <mainReferent begin="55" end="60">birds</mainReferent>
    <tokens>breeding in a southern climate</tokens>
    <annotation annotator="predicted" seType="GENERIC_SENTENCE"/>
  </segment>
  <segment instanceid="a_book_of_natural_history_35.txt_2" begin="92" end="101">
    <text>construct</text>
    <mainVerb begin="92" end="101">construct</mainVerb>
    <mainReferent begin="55" end="60">birds</mainReferent>
    <tokens>The same birds construct far less elaborate nests when breeding in a northern climate</tokens>
    <annotation annotator="predicted" seType="GENERIC_SENTENCE"/>
  </segment>
  <segment instanceid="a_book_of_natural_history_35.txt_3" begin="206" end="213">
    <text>abandon</text>
    <mainVerb begin="206" end="213">abandon</mainVerb>
    <mainReferent begin="179" end="186">species</mainReferent>
    <tokens>Certain species of water-fowl abandon their eggs to the sand and the sun in the warmer zones</tokens>
    <annotation annotator="predicted" seType="GENERIC_SENTENCE"/>
  </segment>
  <segment instanceid="a_book_of_natural_history_35.txt_4" begin="271" end="276">
    <text>build</text>
    <mainVerb begin="271" end="276">build</mainVerb>
    <mainReferent begin="179" end="186">species</mainReferent>
    <tokens>Certain species of water-fowl build a nest</tokens>
    <annotation annotator="predicted" seType="GENERIC_SENTENCE"/>
  </segment>
  <segment instanceid="a_book_of_natural_history_35.txt_5" begin="288" end="291">
    <text>sit</text>
    <mainVerb begin="288" end="291">sit</mainVerb>
    <mainReferent begin="179" end="186">species</mainReferent>
    <tokens>Certain species of water-fowl sit in the usual way in Labrador</tokens>
    <annotation annotator="predicted" seType="GENERIC_SENTENCE"/>
  </segment>
  <segment instanceid="a_book_of_natural_history_35.txt_6" begin="356" end="362">
    <text>places</text>
    <mainVerb begin="356" end="362">places</mainVerb>
    <mainReferent begin="349" end="355">oriole</mainReferent>
    <tokens>In Georgia the Baltimore oriole places its nest upon the north side of the tree</tokens>
    <annotation annotator="predicted" seType="GENERIC_SENTENCE"/>
  </segment>
  <segment instanceid="a_book_of_natural_history_35.txt_7" begin="443" end="448">
    <text>fixes</text>
    <mainVerb begin="443" end="448">fixes</mainVerb>
    <mainReferent begin="440" end="442">it</mainReferent>
    <tokens>in the Middle and Eastern States it fixes it upon the south or east side</tokens>
    <annotation annotator="predicted" seType="GENERIC_SENTENCE"/>
  </segment>
  <segment instanceid="a_book_of_natural_history_35.txt_8" begin="486" end="491">
    <text>makes</text>
    <mainVerb begin="486" end="491">makes</mainVerb>
    <mainReferent begin="440" end="442">it</mainReferent>
    <tokens>it makes it much thicker Warner</tokens>
    <annotation annotator="predicted" seType="GENERIC_SENTENCE"/>
  </segment>
  <segment instanceid="a_book_of_natural_history_35.txt_9" begin="528" end="532">
    <text>seen</text>
    <mainVerb begin="528" end="532">seen</mainVerb>
    <mainReferent begin="520" end="521">I</mainReferent>
    <tokens>I have seen one from the South</tokens>
    <annotation annotator="predicted" seType="STATE"/>
  </segment>
  <segment instanceid="a_book_of_natural_history_35.txt_10" begin="557" end="560">
    <text>had</text>
    <mainVerb begin="557" end="560">had</mainVerb>
    <mainReferent begin="533" end="536">one</mainReferent>
    <tokens>one from the South had some kind-of coarse reed sedge</tokens>
    <annotation annotator="predicted" seType="STATE"/>
  </segment>
  <segment instanceid="a_book_of_natural_history_35.txt_11" begin="596" end="601">
    <text>woven</text>
    <mainVerb begin="596" end="601">woven</mainVerb>
    <mainReferent begin="581" end="585">reed</mainReferent>
    <tokens>woven into it</tokens>
    <annotation annotator="predicted" seType="STATE"/>
  </segment>
  <segment instanceid="a_book_of_natural_history_35.txt_12" begin="611" end="617">
    <text>giving</text>
    <mainVerb begin="611" end="617">giving</mainVerb>
    <mainReferent begin="520" end="521">I</mainReferent>
    <tokens>giving it an open-work appearance like a basket</tokens>
    <annotation annotator="predicted" seType="EVENT"/>
  </segment>
  <segment instanceid="a_book_of_natural_history_35.txt_13" begin="682" end="685">
    <text>use</text>
    <mainVerb begin="682" end="685">use</mainVerb>
    <mainReferent begin="674" end="681">species</mainReferent>
    <tokens>Very few species use the same material uniformly</tokens>
    <annotation annotator="predicted" seType="GENERIC_SENTENCE"/>
  </segment>
  <segment instanceid="a_book_of_natural_history_35.txt_14" begin="722" end="726">
    <text>seen</text>
    <mainVerb begin="722" end="726">seen</mainVerb>
    <mainReferent begin="715" end="716">I</mainReferent>
    <tokens>I have seen the nest of the robin quite destitute of mud</tokens>
    <annotation annotator="predicted" seType="STATE"/>
  </segment>
  <segment instanceid="a_book_of_natural_history_35.txt_15" begin="798" end="806">
    <text>composed</text>
    <mainVerb begin="798" end="806">composed</mainVerb>
    <mainReferent begin="791" end="793">it</mainReferent>
    <tokens>In one instance it was composed mainly of long , black horse-hairs with a lining of fine yellow grass the whole presenting quite a novel appearance</tokens>
    <annotation annotator="predicted" seType="EVENT"/>
  </segment>
  <segment instanceid="a_book_of_natural_history_35.txt_16" begin="843" end="851">
    <text>arranged</text>
    <mainVerb begin="843" end="851">arranged</mainVerb>
    <mainReferent begin="798" end="806">composed</mainReferent>
    <tokens>arranged in a circular manner</tokens>
    <annotation annotator="predicted" seType="EVENT"/>
  </segment>
  <segment instanceid="a_book_of_natural_history_35.txt_17" begin="985" end="988">
    <text>was</text>
    <mainVerb begin="985" end="988">was</mainVerb>
    <mainReferent begin="980" end="984">nest</mainReferent>
    <tokens>In another case the nest was chiefly of a species of rock moss</tokens>
    <annotation annotator="predicted" seType="STATE"/>
  </segment>
  <segment instanceid="a_book_of_natural_history_35.txt_18" begin="1093" end="1095">
    <text>is</text>
    <mainVerb begin="1093" end="1095">is</mainVerb>
    <mainReferent begin="1044" end="1048">nest</mainReferent>
    <tokens>The nest for the second brood during the same season is often a mere</tokens>
    <annotation annotator="predicted" seType="GENERIC_SENTENCE"/>
  </segment>
  <segment instanceid="a_book_of_natural_history_35.txt_19" begin="1190" end="1195">
    <text>seems</text>
    <mainVerb begin="1190" end="1195">seems</mainVerb>
    <mainReferent begin="1126" end="1131">haste</mainReferent>
    <tokens>The haste of the female to deposit her eggs as the season advances seems very great</tokens>
    <annotation annotator="predicted" seType="STATE"/>
  </segment>
  <segment instanceid="a_book_of_natural_history_35.txt_20" begin="1226" end="1228">
    <text>is</text>
    <mainVerb begin="1226" end="1228">is</mainVerb>
    <mainReferent begin="1216" end="1225">structure</mainReferent>
    <tokens>the structure is to be prematurely finished</tokens>
    <annotation annotator="predicted" seType="STATE"/>
  </segment>
  <segment instanceid="a_book_of_natural_history_35.txt_21" begin="1277" end="1285">
    <text>reminded</text>
    <mainVerb begin="1277" end="1285">reminded</mainVerb>
    <mainReferent begin="1262" end="1263">I</mainReferent>
    <tokens>I was recently reminded of this fact happening about the last of July to meet with several nests of the wood or bush sparrow in a remote blackberry field</tokens>
    <annotation annotator="predicted" seType="EVENT"/>
  </segment>
  <segment instanceid="a_book_of_natural_history_35.txt_22" begin="1444" end="1448">
    <text>were</text>
    <mainVerb begin="1444" end="1448">were</mainVerb>
    <mainReferent begin="1428" end="1433">nests</mainReferent>
    <tokens>The nests with eggs were far less compact than the earlier nests , from which the young had flown</tokens>
    <annotation annotator="predicted" seType="STATE"/>
  </segment>
  <segment instanceid="a_book_of_natural_history_35.txt_23" begin="1531" end="1536">
    <text>flown</text>
    <mainVerb begin="1531" end="1536">flown</mainVerb>
    <mainReferent begin="1520" end="1525">young</mainReferent>
    <tokens>than the earlier nests , from which the young had flown</tokens>
    <annotation annotator="predicted" seType="STATE"/>
  </segment>
  <segment instanceid="a_book_of_natural_history_35.txt_24" begin="1561" end="1563">
    <text>go</text>
    <mainVerb begin="1561" end="1563">go</mainVerb>
    <mainReferent begin="1559" end="1560">I</mainReferent>
    <tokens>as I go to a certain piece of woods</tokens>
    <annotation annotator="predicted" seType="EVENT"/>
  </segment>
  <segment instanceid="a_book_of_natural_history_35.txt_25" begin="1595" end="1602">
    <text>observe</text>
    <mainVerb begin="1595" end="1602">observe</mainVerb>
    <mainReferent begin="1593" end="1594">I</mainReferent>
    <tokens>Day after day I observe a male indigo-bird sitting on precisely the same part of a high branch singing in his most vivacious style</tokens>
    <annotation annotator="predicted" seType="EVENT"/>
  </segment>
  <segment instanceid="a_book_of_natural_history_35.txt_26" begin="1723" end="1731">
    <text>approach</text>
    <mainVerb begin="1723" end="1731">approach</mainVerb>
    <mainReferent begin="1721" end="1722">I</mainReferent>
    <tokens>As I approach</tokens>
    <annotation annotator="predicted" seType="EVENT"/>
  </segment>
  <segment instanceid="a_book_of_natural_history_35.txt_27" begin="1736" end="1742">
    <text>ceases</text>
    <mainVerb begin="1736" end="1742">ceases</mainVerb>
    <mainReferent begin="1733" end="1735">he</mainReferent>
    <tokens>he ceases to sing flirting his tail right left with marked emphasis</tokens>
    <annotation annotator="predicted" seType="STATE"/>
  </segment>
  <segment instanceid="a_book_of_natural_history_35.txt_28" begin="1796" end="1802">
    <text>marked</text>
    <mainVerb begin="1796" end="1802">marked</mainVerb>
    <tokens>marked</tokens>
    <annotation annotator="predicted" seType="STATE"/>
  </segment>
  <segment instanceid="a_book_of_natural_history_35.txt_29" begin="1813" end="1819">
    <text>chirps</text>
    <mainVerb begin="1813" end="1819">chirps</mainVerb>
    <mainReferent begin="1723" end="1731">approach</mainReferent>
    <tokens>chirps sharply</tokens>
    <annotation annotator="predicted" seType="STATE"/>
  </segment>
  <segment instanceid="a_book_of_natural_history_35.txt_30" begin="1855" end="1859">
    <text>come</text>
    <mainVerb begin="1855" end="1859">come</mainVerb>
    <mainReferent begin="1853" end="1854">I</mainReferent>
    <tokens>In a low bush near by I come upon the object of his solicitude , a thick , compact nest , composed largely of dry leaves and fine grass , in which a plain brown bird is sitting upon four pale blue eggs</tokens>
    <annotation annotator="predicted" seType="STATE"/>
  </segment>
  <segment instanceid="a_book_of_natural_history_35.txt_31" begin="1919" end="1927">
    <text>composed</text>
    <mainVerb begin="1919" end="1927">composed</mainVerb>
    <mainReferent begin="1913" end="1917">nest</mainReferent>
    <tokens>composed largely of dry leaves and fine grass</tokens>
    <annotation annotator="predicted" seType="GENERIC_SENTENCE"/>
  </segment>
  <segment instanceid="a_book_of_natural_history_35.txt_32" begin="1998" end="2005">
    <text>sitting</text>
    <mainVerb begin="1998" end="2005">sitting</mainVerb>
    <mainReferent begin="1990" end="1994">bird</mainReferent>
    <tokens>of his solicitude , a thick , compact nest , composed largely of dry leaves and fine grass , in which a plain brown bird is sitting upon four pale blue eggs</tokens>
    <annotation annotator="predicted" seType="GENERIC_SENTENCE"/>
  </segment>
  <segment instanceid="a_book_of_natural_history_35.txt_33" begin="2047" end="2049">
    <text>is</text>
    <mainVerb begin="2047" end="2049">is</mainVerb>
    <mainReferent begin="2040" end="2046">wonder</mainReferent>
    <tokens>The wonder is to place its nest in the way of the many dangers that walk and crawl upon the ground</tokens>
    <annotation annotator="predicted" seType="STATE"/>
  </segment>
  <segment instanceid="a_book_of_natural_history_35.txt_34" begin="2068" end="2073">
    <text>leave</text>
    <mainVerb begin="2068" end="2073">leave</mainVerb>
    <mainReferent begin="2058" end="2062">bird</mainReferent>
    <tokens>that a bird will leave the apparent security of the tree-tops</tokens>
    <annotation annotator="predicted" seType="STATE"/>
  </segment>
  <segment instanceid="a_book_of_natural_history_35.txt_35" begin="2169" end="2173">
    <text>walk</text>
    <mainVerb begin="2169" end="2173">walk</mainVerb>
    <mainReferent begin="2156" end="2163">dangers</mainReferent>
    <tokens>the many dangers walk</tokens>
    <annotation annotator="predicted" seType="EVENT"/>
  </segment>
  <segment instanceid="a_book_of_natural_history_35.txt_36" begin="2179" end="2184">
    <text>crawl</text>
    <mainVerb begin="2179" end="2184">crawl</mainVerb>
    <mainReferent begin="2156" end="2163">dangers</mainReferent>
    <tokens>the many dangers crawl upon the ground</tokens>
    <annotation annotator="predicted" seType="GENERIC_SENTENCE"/>
  </segment>
  <segment instanceid="a_book_of_natural_history_35.txt_37" begin="2227" end="2232">
    <text>sings</text>
    <mainVerb begin="2227" end="2232">sings</mainVerb>
    <mainReferent begin="2237" end="2241">bird</mainReferent>
    <tokens>There far of reach sings the bird helpless young</tokens>
    <annotation annotator="predicted" seType="GENERIC_SENTENCE"/>
  </segment>
  <segment instanceid="a_book_of_natural_history_35.txt_38" begin="2282" end="2285">
    <text>are</text>
    <mainVerb begin="2282" end="2285">are</mainVerb>
    <tokens>here not three feet from the ground are its helpless young</tokens>
    <annotation annotator="predicted" seType="GENERIC_SENTENCE"/>
  </segment>
  <segment instanceid="a_book_of_natural_history_35.txt_39" begin="2325" end="2327">
    <text>is</text>
    <mainVerb begin="2325" end="2327">is</mainVerb>
    <mainReferent begin="2319" end="2324">truth</mainReferent>
    <tokens>The truth is</tokens>
    <annotation annotator="predicted" seType="STATE"/>
  </segment>
  <segment instanceid="a_book_of_natural_history_35.txt_40" begin="2335" end="2338">
    <text>are</text>
    <mainVerb begin="2335" end="2338">are</mainVerb>
    <mainReferent begin="2329" end="2334">birds</mainReferent>
    <tokens>birds are the greatest of birds</tokens>
    <annotation annotator="predicted" seType="GENERIC_SENTENCE"/>
  </segment>
  <segment instanceid="a_book_of_natural_history_35.txt_41" begin="2377" end="2379">
    <text>is</text>
    <mainVerb begin="2377" end="2379">is</mainVerb>
    <mainReferent begin="2319" end="2324">truth</mainReferent>
    <tokens>it is with reference to this fact that many of the smaller species build</tokens>
    <annotation annotator="predicted" seType="GENERIC_SENTENCE"/>
  </segment>
  <segment instanceid="a_book_of_natural_history_35.txt_42" begin="2442" end="2447">
    <text>build</text>
    <mainVerb begin="2442" end="2447">build</mainVerb>
    <mainReferent begin="2414" end="2418">many</mainReferent>
    <tokens>that many of the smaller species build</tokens>
    <annotation annotator="predicted" seType="GENERIC_SENTENCE"/>
  </segment>
  <segment instanceid="a_book_of_natural_history_35.txt_43" begin="2562" end="2567">
    <text>known</text>
    <mainVerb begin="2562" end="2567">known</mainVerb>
    <mainReferent begin="2554" end="2555">I</mainReferent>
    <tokens>I have known the ruffed grouse to come out of a dense wood</tokens>
    <annotation annotator="predicted" seType="STATE"/>
  </segment>
  <segment instanceid="a_book_of_natural_history_35.txt_44" begin="2618" end="2622">
    <text>make</text>
    <mainVerb begin="2618" end="2622">make</mainVerb>
    <mainReferent begin="2554" end="2555">I</mainReferent>
    <tokens>make its nest at the root of a tree within ten paces of the road , where , no doubt , hawks and crows , as well as skunks and foxes , would be less liable to find it out</tokens>
    <annotation annotator="predicted" seType="STATE"/>
  </segment>
  <segment instanceid="a_book_of_natural_history_35.txt_45" begin="2755" end="2757">
    <text>be</text>
    <mainVerb begin="2755" end="2757">be</mainVerb>
    <mainReferent begin="2713" end="2718">crows</mainReferent>
    <tokens>where no doubt hawks crows skunks foxes would be less to find it out</tokens>
    <annotation annotator="predicted" seType="STATE"/>
  </segment>
  <segment instanceid="a_book_of_natural_history_35.txt_46" begin="2787" end="2797">
    <text>Traversing</text>
    <mainVerb begin="2787" end="2797">Traversing</mainVerb>
    <mainReferent begin="2841" end="2842">I</mainReferent>
    <tokens>Traversing remote mountain-roads through dense woods</tokens>
    <annotation annotator="predicted" seType="EVENT"/>
  </segment>
  <segment instanceid="a_book_of_natural_history_35.txt_47" begin="2860" end="2864">
    <text>seen</text>
    <mainVerb begin="2860" end="2864">seen</mainVerb>
    <mainReferent begin="2841" end="2842">I</mainReferent>
    <tokens>I have repeatedly seen the veery , or Wilson 's thrush , sitting upon her nest , so near me</tokens>
    <annotation annotator="predicted" seType="STATE"/>
  </segment>
  <segment instanceid="a_book_of_natural_history_35.txt_48" begin="2896" end="2903">
    <text>sitting</text>
    <mainVerb begin="2896" end="2903">sitting</mainVerb>
    <mainReferent begin="2888" end="2894">thrush</mainReferent>
    <tokens>sitting upon her nest</tokens>
    <annotation annotator="predicted" seType="STATE"/>
  </segment>
  <segment instanceid="a_book_of_natural_history_35.txt_49" begin="2951" end="2955">
    <text>take</text>
    <mainVerb begin="2951" end="2955">take</mainVerb>
    <mainReferent begin="2936" end="2937">I</mainReferent>
    <tokens>that I could almost take her from it stretching out my hand</tokens>
    <annotation annotator="predicted" seType="STATE"/>
  </segment>
  <segment instanceid="a_book_of_natural_history_35.txt_50" begin="3010" end="3014">
    <text>show</text>
    <mainVerb begin="3010" end="3014">show</mainVerb>
    <mainReferent begin="2996" end="3001">Birds</mainReferent>
    <tokens>Birds of prey show none of this confidence in man</tokens>
    <annotation annotator="predicted" seType="GENERIC_SENTENCE"/>
  </segment>
  <segment instanceid="a_book_of_natural_history_35.txt_51" begin="3080" end="3085">
    <text>avoid</text>
    <mainVerb begin="3080" end="3085">avoid</mainVerb>
    <mainReferent begin="2996" end="3001">Birds</mainReferent>
    <tokens>Birds of prey when locating their nests avoid</tokens>
    <annotation annotator="predicted" seType="GENERIC_SENTENCE"/>
  </segment>
  <segment instanceid="a_book_of_natural_history_35.txt_52" begin="3098" end="3102">
    <text>seek</text>
    <mainVerb begin="3098" end="3102">seek</mainVerb>
    <mainReferent begin="2996" end="3001">Birds</mainReferent>
    <tokens>seek his haunts</tokens>
    <annotation annotator="predicted" seType="GENERIC_SENTENCE"/>
  </segment>
  <segment instanceid="a_book_of_natural_history_35.txt_53" begin="3171" end="3175">
    <text>know</text>
    <mainVerb begin="3171" end="3175">know</mainVerb>
    <mainReferent begin="3169" end="3170">I</mainReferent>
    <tokens>In a certain locality in the interior of New York I know every season</tokens>
    <annotation annotator="predicted" seType="STATE"/>
  </segment>
  <segment instanceid="a_book_of_natural_history_35.txt_54" begin="3200" end="3202">
    <text>am</text>
    <mainVerb begin="3200" end="3202">am</mainVerb>
    <mainReferent begin="3198" end="3199">I</mainReferent>
    <tokens>where I am to find a nest or two of the slate-colored snow-bird</tokens>
    <annotation annotator="predicted" seType="STATE"/>
  </segment>
  <segment instanceid="a_book_of_natural_history_35.txt_55" begin="3266" end="3268">
    <text>is</text>
    <mainVerb begin="3266" end="3268">is</mainVerb>
    <mainReferent begin="3263" end="3265">It</mainReferent>
    <tokens>It is under the brink of a low , mossy bank so near the highway</tokens>
    <annotation annotator="predicted" seType="STATE"/>
  </segment>
  <segment instanceid="a_book_of_natural_history_35.txt_56" begin="3345" end="3352">
    <text>reached</text>
    <mainVerb begin="3345" end="3352">reached</mainVerb>
    <mainReferent begin="3333" end="3335">it</mainReferent>
    <tokens>that it could be reached from a passing vehicle with a whip</tokens>
    <annotation annotator="predicted" seType="STATE"/>
  </segment>
  <segment instanceid="a_book_of_natural_history_35.txt_57" begin="3429" end="3437">
    <text>disturbs</text>
    <mainVerb begin="3429" end="3437">disturbs</mainVerb>
    <mainReferent begin="3396" end="3401">horse</mainReferent>
    <tokens>foot passenger disturbs the sitting bird</tokens>
    <annotation annotator="predicted" seType="GENERIC_SENTENCE"/>
  </segment>
  <segment instanceid="a_book_of_natural_history_35.txt_58" begin="3461" end="3467">
    <text>awaits</text>
    <mainVerb begin="3461" end="3467">awaits</mainVerb>
    <mainReferent begin="3456" end="3459">She</mainReferent>
    <tokens>She awaits the near approach of a sound of feet or wheels</tokens>
    <annotation annotator="predicted" seType="STATE"/>
  </segment>
  <segment instanceid="a_book_of_natural_history_35.txt_59" begin="3525" end="3530">
    <text>darts</text>
    <mainVerb begin="3525" end="3530">darts</mainVerb>
    <mainReferent begin="3456" end="3459">She</mainReferent>
    <tokens>She then darts quickly across the road</tokens>
    <annotation annotator="predicted" seType="EVENT"/>
  </segment>
  <segment instanceid="a_book_of_natural_history_35.txt_60" begin="3564" end="3572">
    <text>clearing</text>
    <mainVerb begin="3564" end="3572">clearing</mainVerb>
    <tokens>barely clearing the ground</tokens>
    <annotation annotator="predicted" seType="EVENT"/>
  </segment>
  <segment instanceid="a_book_of_natural_history_35.txt_61" begin="3589" end="3599">
    <text>disappears</text>
    <mainVerb begin="3589" end="3599">disappears</mainVerb>
    <mainReferent begin="3456" end="3459">She</mainReferent>
    <tokens>She disappears amid the bushes on the opposite side</tokens>
    <annotation annotator="predicted" seType="EVENT"/>
  </segment>
  <segment instanceid="a_book_of_natural_history_35.txt_62" begin="3660" end="3664">
    <text>line</text>
    <mainVerb begin="3660" end="3664">line</mainVerb>
    <mainReferent begin="3649" end="3654">trees</mainReferent>
    <tokens>the trees line one of the main streets and fashionable drives of Washington city less than half a mile from the boundary</tokens>
    <annotation annotator="predicted" seType="STATE"/>
  </segment>
  <segment instanceid="a_book_of_natural_history_35.txt_63" begin="3713" end="3720">
    <text>leading</text>
    <mainVerb begin="3713" end="3720">leading</mainVerb>
    <tokens>leading out</tokens>
    <annotation annotator="predicted" seType="STATE"/>
  </segment>
  <segment instanceid="a_book_of_natural_history_35.txt_64" begin="3798" end="3805">
    <text>counted</text>
    <mainVerb begin="3798" end="3805">counted</mainVerb>
    <mainReferent begin="3791" end="3792">I</mainReferent>
    <tokens>In the trees that line one of the main streets and fashionable drives leading out of Washington city , and less than half a mile from the boundary I have counted the nests of five different species at one time , and that without any very close scrutiny of the foliage</tokens>
    <annotation annotator="predicted" seType="STATE"/>
  </segment>
  <segment instanceid="a_book_of_natural_history_35.txt_65" begin="3966" end="3974">
    <text>searched</text>
    <mainVerb begin="3966" end="3974">searched</mainVerb>
    <mainReferent begin="3964" end="3965">I</mainReferent>
    <tokens>while in many acres of woodland , half a mile off I searched in vain for a single nest</tokens>
    <annotation annotator="predicted" seType="EVENT"/>
  </segment>
  <segment instanceid="a_book_of_natural_history_35.txt_66" begin="4023" end="4033">
    <text>interested</text>
    <mainVerb begin="4023" end="4033">interested</mainVerb>
    <mainReferent begin="4013" end="4017">five</mainReferent>
    <tokens>the five interested me most</tokens>
    <annotation annotator="predicted" seType="EVENT"/>
  </segment>
  <segment instanceid="a_book_of_natural_history_35.txt_67" begin="4042" end="4045">
    <text>was</text>
    <mainVerb begin="4042" end="4045">was</mainVerb>
    <mainReferent begin="4046" end="4050">that</mainReferent>
    <tokens>Among the five that interested me most was that of a blue grossbeak</tokens>
    <annotation annotator="predicted" seType="STATE"/>
  </segment>
  <segment instanceid="a_book_of_natural_history_35.txt_68" begin="4147" end="4149">
    <text>is</text>
    <mainVerb begin="4147" end="4149">is</mainVerb>
    <mainReferent begin="4083" end="4087">bird</mainReferent>
    <tokens>this bird to Audubon observations in Louisiana is</tokens>
    <annotation annotator="predicted" seType="GENERIC_SENTENCE"/>
  </segment>
  <segment instanceid="a_book_of_natural_history_35.txt_69" begin="4158" end="4165">
    <text>recluse</text>
    <mainVerb begin="4158" end="4165">recluse</mainVerb>
    <mainReferent begin="4083" end="4087">bird</mainReferent>
    <tokens>this bird recluse</tokens>
    <annotation annotator="predicted" seType="GENERIC_SENTENCE"/>
  </segment>
  <segment instanceid="a_book_of_natural_history_35.txt_70" begin="4167" end="4176">
    <text>affecting</text>
    <mainVerb begin="4167" end="4176">affecting</mainVerb>
    <mainReferent begin="4083" end="4087">bird</mainReferent>
    <tokens>affecting remote marshes the borders of large ponds of stagnant water</tokens>
    <annotation annotator="predicted" seType="GENERIC_SENTENCE"/>
  </segment>
  <segment instanceid="a_book_of_natural_history_35.txt_71" begin="4247" end="4253">
    <text>placed</text>
    <mainVerb begin="4247" end="4253">placed</mainVerb>
    <mainReferent begin="4083" end="4087">bird</mainReferent>
    <tokens>Here this bird had placed its nest in the lowest twig of the lowest branch of a large sycamore immediately over a great thoroughfare near the ground that a person standing in a cart or sitting on a horse could have reached it with his hand</tokens>
    <annotation annotator="predicted" seType="GENERIC_SENTENCE"/>
  </segment>
  <segment instanceid="a_book_of_natural_history_35.txt_72" begin="4455" end="4462">
    <text>reached</text>
    <mainVerb begin="4455" end="4462">reached</mainVerb>
    <mainReferent begin="4381" end="4387">ground</mainReferent>
    <tokens>that a person standing in a cart sitting on a horse could have reached it with his hand</tokens>
    <annotation annotator="predicted" seType="GENERIC_SENTENCE"/>
  </segment>
  <segment instanceid="a_book_of_natural_history_35.txt_73" begin="4495" end="4503">
    <text>composed</text>
    <mainVerb begin="4495" end="4503">composed</mainVerb>
    <mainReferent begin="4486" end="4490">nest</mainReferent>
    <tokens>The nest was composed mainly of fragments of newspaper and stalks of grass , though so low</tokens>
    <annotation annotator="predicted" seType="GENERIC_SENTENCE"/>
  </segment>
  <segment instanceid="a_book_of_natural_history_35.txt_74" begin="4599" end="4608">
    <text>concealed</text>
    <mainVerb begin="4599" end="4608">concealed</mainVerb>
    <mainReferent begin="4486" end="4490">nest</mainReferent>
    <tokens>The nest was remarkably well concealed one of the peculiar clusters of twigs and leaves which characterize this tree</tokens>
    <annotation annotator="predicted" seType="GENERIC_SENTENCE"/>
  </segment>
  <segment instanceid="a_book_of_natural_history_35.txt_75" begin="4668" end="4680">
    <text>characterize</text>
    <mainVerb begin="4668" end="4680">characterize</mainVerb>
    <mainReferent begin="4633" end="4641">clusters</mainReferent>
    <tokens>the peculiar clusters of twigs and leaves characterize this tree</tokens>
    <annotation annotator="predicted" seType="GENERIC_SENTENCE"/>
  </segment>
  <segment instanceid="a_book_of_natural_history_35.txt_76" begin="4702" end="4711">
    <text>contained</text>
    <mainVerb begin="4702" end="4711">contained</mainVerb>
    <mainReferent begin="4697" end="4701">nest</mainReferent>
    <tokens>The nest contained young</tokens>
    <annotation annotator="predicted" seType="STATE"/>
  </segment>
  <segment instanceid="a_book_of_natural_history_35.txt_77" begin="4725" end="4735">
    <text>discovered</text>
    <mainVerb begin="4725" end="4735">discovered</mainVerb>
    <mainReferent begin="4723" end="4724">I</mainReferent>
    <tokens>when I discovered it</tokens>
    <annotation annotator="predicted" seType="EVENT"/>
  </segment>
  <segment instanceid="a_book_of_natural_history_35.txt_78" begin="4769" end="4773">
    <text>were</text>
    <mainVerb begin="4769" end="4773">were</mainVerb>
    <mainReferent begin="4763" end="4768">birds</mainReferent>
    <tokens>though the parent birds were much by my loitering about beneath the tree</tokens>
    <annotation annotator="predicted" seType="STATE"/>
  </segment>
  <segment instanceid="a_book_of_natural_history_35.txt_79" begin="4833" end="4837">
    <text>paid</text>
    <mainVerb begin="4833" end="4837">paid</mainVerb>
    <mainReferent begin="4697" end="4701">nest</mainReferent>
    <tokens>they paid little attention to the stream of vehicles that was constantly passing</tokens>
    <annotation annotator="predicted" seType="EVENT"/>
  </segment>
  <segment instanceid="a_book_of_natural_history_35.txt_80" begin="4902" end="4909">
    <text>passing</text>
    <mainVerb begin="4902" end="4909">passing</mainVerb>
    <mainReferent begin="4872" end="4880">vehicles</mainReferent>
    <tokens>vehicles was constantly passing</tokens>
    <annotation annotator="predicted" seType="GENERALIZING_SENTENCE"/>
  </segment>
  <segment instanceid="a_book_of_natural_history_35.txt_81" begin="4914" end="4916">
    <text>is</text>
    <mainVerb begin="4914" end="4916">is</mainVerb>
    <mainReferent begin="4911" end="4913">It</mainReferent>
    <tokens>It is a to me</tokens>
    <annotation annotator="predicted" seType="STATE"/>
  </segment>
  <segment instanceid="a_book_of_natural_history_35.txt_82" begin="4958" end="4963">
    <text>built</text>
    <mainVerb begin="4958" end="4963">built</mainVerb>
    <mainReferent begin="4941" end="4946">birds</mainReferent>
    <tokens>when the birds could have built it</tokens>
    <annotation annotator="predicted" seType="GENERIC_SENTENCE"/>
  </segment>
  <segment instanceid="a_book_of_natural_history_35.txt_83" begin="4978" end="4981">
    <text>are</text>
    <mainVerb begin="4978" end="4981">are</mainVerb>
    <mainReferent begin="4973" end="4977">they</mainReferent>
    <tokens>for they are much when building than at other times</tokens>
    <annotation annotator="predicted" seType="GENERIC_SENTENCE"/>
  </segment>
  <segment instanceid="a_book_of_natural_history_35.txt_84" begin="5043" end="5049">
    <text>worked</text>
    <mainVerb begin="5043" end="5049">worked</mainVerb>
    <mainReferent begin="5031" end="5036">doubt</mainReferent>
    <tokens>No doubt they worked mostly in the morning</tokens>
    <annotation annotator="predicted" seType="EVENT"/>
  </segment>
  <segment instanceid="a_book_of_natural_history_35.txt_85" begin="5073" end="5079">
    <text>having</text>
    <mainVerb begin="5073" end="5079">having</mainVerb>
    <tokens>having the early hours all to themselves</tokens>
    <annotation annotator="predicted" seType="EVENT"/>
  </segment>
</document>
