<?xml version="1.0" encoding="UTF-8"?>

<document>
  <segment instanceid="the_burgess_animal_book_for_children_45.txt_1" begin="4" end="6">
    <text>is</text>
    <mainVerb begin="4" end="6">is</mainVerb>
    <mainReferent begin="1" end="3">It</mainReferent>
    <tokens>It is a</tokens>
    <annotation annotator="predicted" seType="STATE"/>
  </segment>
  <segment instanceid="the_burgess_animal_book_for_children_45.txt_2" begin="26" end="32">
    <text>living</text>
    <mainVerb begin="26" end="32">living</mainVerb>
    <mainReferent begin="16" end="18">he</mainReferent>
    <tokens>he was n't living in Farmer Brown 's house</tokens>
    <annotation annotator="predicted" seType="STATE"/>
  </segment>
  <segment instanceid="the_burgess_animal_book_for_children_45.txt_3" begin="59" end="63">
    <text>said</text>
    <mainVerb begin="59" end="63">said</mainVerb>
    <mainReferent begin="76" end="82">Nature</mainReferent>
    <tokens>“ ” said Old Mother Nature</tokens>
    <annotation annotator="predicted" seType="REPORT"/>
  </segment>
  <segment instanceid="the_burgess_animal_book_for_children_45.txt_4" begin="123" end="127">
    <text>were</text>
    <mainVerb begin="123" end="127">were</mainVerb>
    <mainReferent begin="85" end="86">“</mainReferent>
    <tokens>“ Probably other members of his family were</tokens>
    <annotation annotator="predicted" seType="STATE"/>
  </segment>
  <segment instanceid="the_burgess_animal_book_for_children_45.txt_5" begin="133" end="135">
    <text>is</text>
    <mainVerb begin="133" end="135">is</mainVerb>
    <mainReferent begin="130" end="132">He</mainReferent>
    <tokens>He is perfectly at home in any building put up by man</tokens>
    <annotation annotator="predicted" seType="STATE"/>
  </segment>
  <segment instanceid="the_burgess_animal_book_for_children_45.txt_6" begin="170" end="173">
    <text>put</text>
    <mainVerb begin="170" end="173">put</mainVerb>
    <mainReferent begin="161" end="169">building</mainReferent>
    <tokens>put up man</tokens>
    <annotation annotator="predicted" seType="EVENT"/>
  </segment>
  <segment instanceid="the_burgess_animal_book_for_children_45.txt_7" begin="194" end="196">
    <text>is</text>
    <mainVerb begin="194" end="196">is</mainVerb>
    <tokens>just as is Robber the</tokens>
    <annotation annotator="predicted" seType="STATE"/>
  </segment>
  <segment instanceid="the_burgess_animal_book_for_children_45.txt_8" begin="247" end="249">
    <text>go</text>
    <mainVerb begin="247" end="249">go</mainVerb>
    <mainReferent begin="240" end="242">he</mainReferent>
    <tokens>Because of his small size he can go</tokens>
    <annotation annotator="predicted" seType="STATE"/>
  </segment>
  <segment instanceid="the_burgess_animal_book_for_children_45.txt_9" begin="264" end="267">
    <text>can</text>
    <mainVerb begin="264" end="267">can</mainVerb>
    <mainReferent begin="257" end="263">Robber</mainReferent>
    <tokens>where Robber can not</tokens>
    <annotation annotator="predicted" seType="GENERIC_SENTENCE"/>
  </segment>
  <segment instanceid="the_burgess_animal_book_for_children_45.txt_10" begin="276" end="284">
    <text>delights</text>
    <mainVerb begin="276" end="284">delights</mainVerb>
    <mainReferent begin="273" end="275">He</mainReferent>
    <tokens>He delights</tokens>
    <annotation annotator="predicted" seType="EVENT"/>
  </segment>
  <segment instanceid="the_burgess_animal_book_for_children_45.txt_11" begin="288" end="295">
    <text>scamper</text>
    <mainVerb begin="288" end="295">scamper</mainVerb>
    <mainReferent begin="273" end="275">He</mainReferent>
    <tokens>He to scamper about between the walls</tokens>
    <annotation annotator="predicted" seType="EVENT"/>
  </segment>
  <segment instanceid="the_burgess_animal_book_for_children_45.txt_12" begin="356" end="363">
    <text>gnawing</text>
    <mainVerb begin="356" end="363">gnawing</mainVerb>
    <mainReferent begin="342" end="344">he</mainReferent>
    <tokens>he is forever gnawing holes in the corners of rooms opening on to pantry shelves</tokens>
    <annotation annotator="predicted" seType="EVENT"/>
  </segment>
  <segment instanceid="the_burgess_animal_book_for_children_45.txt_13" begin="443" end="448">
    <text>steal</text>
    <mainVerb begin="443" end="448">steal</mainVerb>
    <mainReferent begin="436" end="438">he</mainReferent>
    <tokens>so that he may steal food</tokens>
    <annotation annotator="predicted" seType="STATE"/>
  </segment>
  <segment instanceid="the_burgess_animal_book_for_children_45.txt_14" begin="460" end="464">
    <text>eats</text>
    <mainVerb begin="460" end="464">eats</mainVerb>
    <mainReferent begin="457" end="459">He</mainReferent>
    <tokens>He eats all sorts of food</tokens>
    <annotation annotator="predicted" seType="GENERALIZING_SENTENCE"/>
  </segment>
  <segment instanceid="the_burgess_animal_book_for_children_45.txt_15" begin="488" end="494">
    <text>spoils</text>
    <mainVerb begin="488" end="494">spoils</mainVerb>
    <mainReferent begin="457" end="459">He</mainReferent>
    <tokens>He spoils more for man by running about over it</tokens>
    <annotation annotator="predicted" seType="GENERALIZING_SENTENCE"/>
  </segment>
  <segment instanceid="the_burgess_animal_book_for_children_45.txt_16" begin="544" end="548">
    <text>eats</text>
    <mainVerb begin="544" end="548">eats</mainVerb>
    <mainReferent begin="541" end="543">he</mainReferent>
    <tokens>than he eats</tokens>
    <annotation annotator="predicted" seType="GENERALIZING_SENTENCE"/>
  </segment>
  <segment instanceid="the_burgess_animal_book_for_children_45.txt_17" begin="578" end="582">
    <text>gets</text>
    <mainVerb begin="578" end="582">gets</mainVerb>
    <mainReferent begin="574" end="576">he</mainReferent>
    <tokens>In barns and henhouses he gets into the grain bins</tokens>
    <annotation annotator="predicted" seType="GENERALIZING_SENTENCE"/>
  </segment>
  <segment instanceid="the_burgess_animal_book_for_children_45.txt_18" begin="607" end="613">
    <text>steals</text>
    <mainVerb begin="607" end="613">steals</mainVerb>
    <mainReferent begin="574" end="576">he</mainReferent>
    <tokens>he steals a great deal of grain</tokens>
    <annotation annotator="predicted" seType="EVENT"/>
  </segment>
  <segment instanceid="the_burgess_animal_book_for_children_45.txt_19" begin="644" end="646">
    <text>is</text>
    <mainVerb begin="644" end="646">is</mainVerb>
    <mainReferent begin="641" end="643">It</mainReferent>
    <tokens>“ It is largely because of Robber the Rat and Nibbler</tokens>
    <annotation annotator="predicted" seType="STATE"/>
  </segment>
  <segment instanceid="the_burgess_animal_book_for_children_45.txt_20" begin="702" end="706">
    <text>keep</text>
    <mainVerb begin="702" end="706">keep</mainVerb>
    <mainReferent begin="698" end="701">men</mainReferent>
    <tokens>that men keep the Cats you all hate so</tokens>
    <annotation annotator="predicted" seType="GENERIC_SENTENCE"/>
  </segment>
  <segment instanceid="the_burgess_animal_book_for_children_45.txt_21" begin="741" end="743">
    <text>is</text>
    <mainVerb begin="741" end="743">is</mainVerb>
    <mainReferent begin="737" end="740">Cat</mainReferent>
    <tokens>A Cat is Nibbler worst</tokens>
    <annotation annotator="predicted" seType="GENERIC_SENTENCE"/>
  </segment>
  <segment instanceid="the_burgess_animal_book_for_children_45.txt_22" begin="777" end="779">
    <text>is</text>
    <mainVerb begin="777" end="779">is</mainVerb>
    <mainReferent begin="768" end="775">Nibbler</mainReferent>
    <tokens>Nibbler is graceful with a long , hairless tail and ears of good size</tokens>
    <annotation annotator="predicted" seType="STATE"/>
  </segment>
  <segment instanceid="the_burgess_animal_book_for_children_45.txt_23" begin="857" end="859">
    <text>is</text>
    <mainVerb begin="857" end="859">is</mainVerb>
    <mainReferent begin="872" end="877">ready</mainReferent>
    <tokens>He is very ready to dart into his hole at the least sound</tokens>
    <annotation annotator="predicted" seType="STATE"/>
  </segment>
  <segment instanceid="the_burgess_animal_book_for_children_45.txt_24" begin="925" end="931">
    <text>raises</text>
    <mainVerb begin="925" end="931">raises</mainVerb>
    <mainReferent begin="922" end="924">He</mainReferent>
    <tokens>He raises from four to nine babies at a time and several sets of them in a year</tokens>
    <annotation annotator="predicted" seType="EVENT"/>
  </segment>
  <segment instanceid="the_burgess_animal_book_for_children_45.txt_25" begin="1036" end="1042">
    <text>living</text>
    <mainVerb begin="1036" end="1042">living</mainVerb>
    <mainReferent begin="1024" end="1031">Nibbler</mainReferent>
    <tokens>“ If Mr. Mrs. Nibbler are living in a house</tokens>
    <annotation annotator="predicted" seType="STATE"/>
  </segment>
  <segment instanceid="the_burgess_animal_book_for_children_45.txt_26" begin="1069" end="1073">
    <text>made</text>
    <mainVerb begin="1069" end="1073">made</mainVerb>
    <mainReferent begin="1061" end="1065">nest</mainReferent>
    <tokens>their nest is made of scraps of paper , cloth , wool and other soft things stolen from the people who live in the house</tokens>
    <annotation annotator="predicted" seType="GENERIC_SENTENCE"/>
  </segment>
  <segment instanceid="the_burgess_animal_book_for_children_45.txt_27" begin="1129" end="1135">
    <text>stolen</text>
    <mainVerb begin="1129" end="1135">stolen</mainVerb>
    <mainReferent begin="1078" end="1084">scraps</mainReferent>
    <tokens>stolen from the people who live in the house</tokens>
    <annotation annotator="predicted" seType="GENERIC_SENTENCE"/>
  </segment>
  <segment instanceid="the_burgess_animal_book_for_children_45.txt_28" begin="1157" end="1161">
    <text>live</text>
    <mainVerb begin="1157" end="1161">live</mainVerb>
    <mainReferent begin="1146" end="1152">people</mainReferent>
    <tokens>the people live in the house</tokens>
    <annotation annotator="predicted" seType="GENERIC_SENTENCE"/>
  </segment>
  <segment instanceid="the_burgess_animal_book_for_children_45.txt_29" begin="1214" end="1216">
    <text>do</text>
    <mainVerb begin="1214" end="1216">do</mainVerb>
    <mainReferent begin="1202" end="1206">they</mainReferent>
    <tokens>getting this material they often do great damage</tokens>
    <annotation annotator="predicted" seType="GENERIC_SENTENCE"/>
  </segment>
  <segment instanceid="the_burgess_animal_book_for_children_45.txt_30" begin="1244" end="1250">
    <text>living</text>
    <mainVerb begin="1244" end="1250">living</mainVerb>
    <mainReferent begin="1235" end="1239">they</mainReferent>
    <tokens>If they are living in a barn</tokens>
    <annotation annotator="predicted" seType="GENERIC_SENTENCE"/>
  </segment>
  <segment instanceid="the_burgess_animal_book_for_children_45.txt_31" begin="1267" end="1271">
    <text>make</text>
    <mainVerb begin="1267" end="1271">make</mainVerb>
    <mainReferent begin="1262" end="1266">they</mainReferent>
    <tokens>they make their nest of hay and any soft material they can find</tokens>
    <annotation annotator="predicted" seType="GENERIC_SENTENCE"/>
  </segment>
  <segment instanceid="the_burgess_animal_book_for_children_45.txt_32" begin="1322" end="1326">
    <text>find</text>
    <mainVerb begin="1322" end="1326">find</mainVerb>
    <mainReferent begin="1313" end="1317">they</mainReferent>
    <tokens>they can find</tokens>
    <annotation annotator="predicted" seType="GENERIC_SENTENCE"/>
  </segment>
  <segment instanceid="the_burgess_animal_book_for_children_45.txt_33" begin="1346" end="1353">
    <text>prefers</text>
    <mainVerb begin="1346" end="1353">prefers</mainVerb>
    <mainReferent begin="1338" end="1345">Nibbler</mainReferent>
    <tokens>“ While Nibbler prefers to live in</tokens>
    <annotation annotator="predicted" seType="STATE"/>
  </segment>
  <segment instanceid="the_burgess_animal_book_for_children_45.txt_34" begin="1368" end="1373">
    <text>close</text>
    <mainVerb begin="1368" end="1373">close</mainVerb>
    <mainReferent begin="1338" end="1345">Nibbler</mainReferent>
    <tokens>Nibbler close to the homes of men</tokens>
    <annotation annotator="predicted" seType="EVENT"/>
  </segment>
  <segment instanceid="the_burgess_animal_book_for_children_45.txt_35" begin="1412" end="1418">
    <text>driven</text>
    <mainVerb begin="1412" end="1418">driven</mainVerb>
    <mainReferent begin="1396" end="1398">he</mainReferent>
    <tokens>he sometimes is driven out especially in summer</tokens>
    <annotation annotator="predicted" seType="GENERALIZING_SENTENCE"/>
  </segment>
  <segment instanceid="the_burgess_animal_book_for_children_45.txt_36" begin="1432" end="1437">
    <text>takes</text>
    <mainVerb begin="1432" end="1437">takes</mainVerb>
    <mainReferent begin="1396" end="1398">he</mainReferent>
    <tokens>he then takes to the fields</tokens>
    <annotation annotator="predicted" seType="GENERALIZING_SENTENCE"/>
  </segment>
  <segment instanceid="the_burgess_animal_book_for_children_45.txt_37" begin="1486" end="1491">
    <text>lives</text>
    <mainVerb begin="1486" end="1491">lives</mainVerb>
    <mainReferent begin="1483" end="1485">he</mainReferent>
    <tokens>There he lives in all sorts of hiding places</tokens>
    <annotation annotator="predicted" seType="STATE"/>
  </segment>
  <segment instanceid="the_burgess_animal_book_for_children_45.txt_38" begin="1527" end="1529">
    <text>is</text>
    <mainVerb begin="1527" end="1529">is</mainVerb>
    <mainReferent begin="1483" end="1485">he</mainReferent>
    <tokens>he is n't at all</tokens>
    <annotation annotator="predicted" seType="STATE"/>
  </segment>
  <segment instanceid="the_burgess_animal_book_for_children_45.txt_39" begin="1567" end="1569">
    <text>is</text>
    <mainVerb begin="1567" end="1569">is</mainVerb>
    <mainReferent begin="1561" end="1566">place</mainReferent>
    <tokens>what the place is</tokens>
    <annotation annotator="predicted" seType="STATE"/>
  </segment>
  <segment instanceid="the_burgess_animal_book_for_children_45.txt_40" begin="1577" end="1585">
    <text>promises</text>
    <mainVerb begin="1577" end="1585">promises</mainVerb>
    <mainReferent begin="1574" end="1576">it</mainReferent>
    <tokens>if it promises</tokens>
    <annotation annotator="predicted" seType="GENERIC_SENTENCE"/>
  </segment>
  <segment instanceid="the_burgess_animal_book_for_children_45.txt_41" begin="1610" end="1618">
    <text>obtained</text>
    <mainVerb begin="1610" end="1618">obtained</mainVerb>
    <mainReferent begin="1586" end="1592">safety</mainReferent>
    <tokens>safety food can be obtained close by</tokens>
    <annotation annotator="predicted" seType="GENERIC_SENTENCE"/>
  </segment>
  <segment instanceid="the_burgess_animal_book_for_children_45.txt_42" begin="1631" end="1633">
    <text>'m</text>
    <mainVerb begin="1631" end="1633">'m</mainVerb>
    <mainReferent begin="1630" end="1631">I</mainReferent>
    <tokens>I 'm</tokens>
    <annotation annotator="predicted" seType="STATE"/>
  </segment>
  <segment instanceid="the_burgess_animal_book_for_children_45.txt_43" begin="1653" end="1657">
    <text>came</text>
    <mainVerb begin="1653" end="1657">came</mainVerb>
    <mainReferent begin="1640" end="1647">Nibbler</mainReferent>
    <tokens>Nibbler ever came to this country</tokens>
    <annotation annotator="predicted" seType="EVENT"/>
  </segment>
  <segment instanceid="the_burgess_animal_book_for_children_45.txt_44" begin="1681" end="1688">
    <text>brought</text>
    <mainVerb begin="1681" end="1688">brought</mainVerb>
    <mainReferent begin="1677" end="1680">Man</mainReferent>
    <tokens>Man brought him here</tokens>
    <annotation annotator="predicted" seType="EVENT"/>
  </segment>
  <segment instanceid="the_burgess_animal_book_for_children_45.txt_45" begin="1709" end="1711">
    <text>is</text>
    <mainVerb begin="1709" end="1711">is</mainVerb>
    <mainReferent begin="1677" end="1680">Man</mainReferent>
    <tokens>now he is here to stay and quite as much at home</tokens>
    <annotation annotator="predicted" seType="STATE"/>
  </segment>
  <segment instanceid="the_burgess_animal_book_for_children_45.txt_46" begin="1761" end="1769">
    <text>belonged</text>
    <mainVerb begin="1761" end="1769">belonged</mainVerb>
    <mainReferent begin="1758" end="1760">he</mainReferent>
    <tokens>as if he belonged here the way</tokens>
    <annotation annotator="predicted" seType="STATE"/>
  </segment>
  <segment instanceid="the_burgess_animal_book_for_children_45.txt_47" begin="1799" end="1801">
    <text>do</text>
    <mainVerb begin="1799" end="1801">do</mainVerb>
    <mainReferent begin="1787" end="1791">rest</mainReferent>
    <tokens>the rest of you do</tokens>
    <annotation annotator="predicted" seType="STATE"/>
  </segment>
  <segment instanceid="the_burgess_animal_book_for_children_45.txt_48" begin="1812" end="1820">
    <text>finishes</text>
    <mainVerb begin="1812" end="1820">finishes</mainVerb>
    <mainReferent begin="1807" end="1811">This</mainReferent>
    <tokens>“ This finishes the lessons on the order of Rodents</tokens>
    <annotation annotator="predicted" seType="STATE"/>
  </segment>
  <segment instanceid="the_burgess_animal_book_for_children_45.txt_49" begin="1871" end="1878">
    <text>related</text>
    <mainVerb begin="1871" end="1878">related</mainVerb>
    <mainReferent begin="1862" end="1869">animals</mainReferent>
    <tokens>the animals related by reason of having teeth for the purpose of gnawing</tokens>
    <annotation annotator="predicted" seType="STATE"/>
  </segment>
  <segment instanceid="the_burgess_animal_book_for_children_45.txt_50" begin="1937" end="1944">
    <text>suspect</text>
    <mainVerb begin="1937" end="1944">suspect</mainVerb>
    <mainReferent begin="1934" end="1935">I</mainReferent>
    <tokens>I suspect so</tokens>
    <annotation annotator="predicted" seType="STATE"/>
  </segment>
  <segment instanceid="the_burgess_animal_book_for_children_45.txt_51" begin="1951" end="1954">
    <text>are</text>
    <mainVerb begin="1951" end="1954">are</mainVerb>
    <mainReferent begin="1945" end="1950">these</mainReferent>
    <tokens>these are the only</tokens>
    <annotation annotator="predicted" seType="STATE"/>
  </segment>
  <segment instanceid="the_burgess_animal_book_for_children_45.txt_52" begin="1981" end="1985">
    <text>take</text>
    <mainVerb begin="1981" end="1985">take</mainVerb>
    <mainReferent begin="1977" end="1980">you</mainReferent>
    <tokens>you take any interest</tokens>
    <annotation annotator="predicted" seType="EVENT"/>
  </segment>
  <segment instanceid="the_burgess_animal_book_for_children_45.txt_53" begin="2021" end="2025">
    <text>care</text>
    <mainVerb begin="2021" end="2025">care</mainVerb>
    <mainReferent begin="2008" end="2011">you</mainReferent>
    <tokens>you will not care to come to school any more</tokens>
    <annotation annotator="predicted" seType="STATE"/>
  </segment>
  <segment instanceid="the_burgess_animal_book_for_children_45.txt_54" begin="2055" end="2057">
    <text>Am</text>
    <mainVerb begin="2055" end="2057">Am</mainVerb>
    <tokens>Am I right ”</tokens>
    <annotation annotator="predicted" seType="STATE"/>
  </segment>
  <segment instanceid="the_burgess_animal_book_for_children_45.txt_55" begin="2083" end="2091">
    <text>answered</text>
    <mainVerb begin="2083" end="2091">answered</mainVerb>
    <mainReferent begin="2072" end="2074">No</mainReferent>
    <tokens>“ No marm ” answered Happy Jack the Gray Squirrel</tokens>
    <annotation annotator="predicted" seType="REPORT"/>
  </segment>
  <segment instanceid="the_burgess_animal_book_for_children_45.txt_56" begin="2131" end="2139">
    <text>remember</text>
    <mainVerb begin="2131" end="2139">remember</mainVerb>
    <mainReferent begin="2127" end="2130">you</mainReferent>
    <tokens>you remember</tokens>
    <annotation annotator="predicted" seType="STATE"/>
  </segment>
  <segment instanceid="the_burgess_animal_book_for_children_45.txt_57" begin="2146" end="2153">
    <text>laughed</text>
    <mainVerb begin="2146" end="2153">laughed</mainVerb>
    <mainReferent begin="2112" end="2120">Squirrel</mainReferent>
    <tokens>the Gray Squirrel had laughed at Peter Rabbit wanting to go to school</tokens>
    <annotation annotator="predicted" seType="EVENT"/>
  </segment>
  <segment instanceid="the_burgess_animal_book_for_children_45.txt_58" begin="2200" end="2201">
    <text>“</text>
    <mainVerb begin="2200" end="2201">“</mainVerb>
    <tokens>“ No marm</tokens>
    <annotation annotator="predicted" seType="STATE"/>
  </segment>
  <segment instanceid="the_burgess_animal_book_for_children_45.txt_59" begin="2218" end="2221">
    <text>are</text>
    <mainVerb begin="2218" end="2221">are</mainVerb>
    <mainReferent begin="2241" end="2247">people</mainReferent>
    <tokens>There are ever so many other people of the Green Forest and the Green Meadows</tokens>
    <annotation annotator="predicted" seType="STATE"/>
  </segment>
  <segment instanceid="the_burgess_animal_book_for_children_45.txt_60" begin="2294" end="2298">
    <text>want</text>
    <mainVerb begin="2294" end="2298">want</mainVerb>
    <mainReferent begin="2291" end="2293">we</mainReferent>
    <tokens>we want to know more about</tokens>
    <annotation annotator="predicted" seType="STATE"/>
  </segment>
  <segment instanceid="the_burgess_animal_book_for_children_45.txt_61" begin="2330" end="2334">
    <text>know</text>
    <mainVerb begin="2330" end="2334">know</mainVerb>
    <mainReferent begin="2312" end="2317">about</mainReferent>
    <tokens>than we now know</tokens>
    <annotation annotator="predicted" seType="STATE"/>
  </segment>
  <segment instanceid="the_burgess_animal_book_for_children_45.txt_62" begin="2337" end="2339">
    <text>Is</text>
    <mainVerb begin="2337" end="2339">Is</mainVerb>
    <mainReferent begin="2352" end="2353">”</mainReferent>
    <tokens>Is n't that</tokens>
    <annotation annotator="predicted" seType="QUESTION"/>
  </segment>
  <segment instanceid="the_burgess_animal_book_for_children_45.txt_63" begin="2352" end="2353">
    <text>”</text>
    <mainVerb begin="2352" end="2353">”</mainVerb>
    <mainReferent begin="2349" end="2351">so</mainReferent>
    <tokens>”</tokens>
    <annotation annotator="predicted" seType="IMPERATIVE"/>
  </segment>
  <segment instanceid="the_burgess_animal_book_for_children_45.txt_64" begin="2366" end="2372">
    <text>turned</text>
    <mainVerb begin="2366" end="2372">turned</mainVerb>
    <mainReferent begin="2361" end="2365">Jack</mainReferent>
    <tokens>Happy Jack turned to the others and every one nodded , even Prickly Porky</tokens>
    <annotation annotator="predicted" seType="EVENT"/>
  </segment>
  <segment instanceid="the_burgess_animal_book_for_children_45.txt_65" begin="2440" end="2442">
    <text>is</text>
    <mainVerb begin="2440" end="2442">is</mainVerb>
    <mainReferent begin="2468" end="2473">right</mainReferent>
    <tokens>“ There is one little fellow living right near here</tokens>
    <annotation annotator="predicted" seType="STATE"/>
  </segment>
  <segment instanceid="the_burgess_animal_book_for_children_45.txt_66" begin="2488" end="2493">
    <text>looks</text>
    <mainVerb begin="2488" end="2493">looks</mainVerb>
    <mainReferent begin="2468" end="2473">right</mainReferent>
    <tokens>one little fellow living right near here looks to me</tokens>
    <annotation annotator="predicted" seType="STATE"/>
  </segment>
  <segment instanceid="the_burgess_animal_book_for_children_45.txt_67" begin="2515" end="2517">
    <text>be</text>
    <mainVerb begin="2515" end="2517">be</mainVerb>
    <mainReferent begin="2507" end="2509">he</mainReferent>
    <tokens>as if he must be a of the Mouse family</tokens>
    <annotation annotator="predicted" seType="STATE"/>
  </segment>
  <segment instanceid="the_burgess_animal_book_for_children_45.txt_68" begin="2555" end="2557">
    <text>is</text>
    <mainVerb begin="2555" end="2557">is</mainVerb>
    <mainReferent begin="2468" end="2473">right</mainReferent>
    <tokens>he is n't like any of the Mice you have told us about</tokens>
    <annotation annotator="predicted" seType="STATE"/>
  </segment>
  <segment instanceid="the_burgess_animal_book_for_children_45.txt_69" begin="2592" end="2596">
    <text>told</text>
    <mainVerb begin="2592" end="2596">told</mainVerb>
    <mainReferent begin="2583" end="2586">you</mainReferent>
    <tokens>of the Mice you have told us about</tokens>
    <annotation annotator="predicted" seType="STATE"/>
  </segment>
  <segment instanceid="the_burgess_animal_book_for_children_45.txt_70" begin="2608" end="2617">
    <text>continued</text>
    <mainVerb begin="2608" end="2617">continued</mainVerb>
    <mainReferent begin="2606" end="2607">”</mainReferent>
    <tokens>” continued Happy Jack</tokens>
    <annotation annotator="predicted" seType="EVENT"/>
  </segment>
  <segment instanceid="the_burgess_animal_book_for_children_45.txt_71" begin="2635" end="2637">
    <text>is</text>
    <mainVerb begin="2635" end="2637">is</mainVerb>
    <mainReferent begin="2631" end="2632">“</mainReferent>
    <tokens>“ He is so</tokens>
    <annotation annotator="predicted" seType="STATE"/>
  </segment>
  <segment instanceid="the_burgess_animal_book_for_children_45.txt_72" begin="2655" end="2659">
    <text>hide</text>
    <mainVerb begin="2655" end="2659">hide</mainVerb>
    <mainReferent begin="2648" end="2650">he</mainReferent>
    <tokens>he can hide under a leaf</tokens>
    <annotation annotator="predicted" seType="STATE"/>
  </segment>
  <segment instanceid="the_burgess_animal_book_for_children_45.txt_73" begin="2676" end="2678">
    <text>'m</text>
    <mainVerb begin="2676" end="2678">'m</mainVerb>
    <mainReferent begin="2675" end="2676">I</mainReferent>
    <tokens>I 'm</tokens>
    <annotation annotator="predicted" seType="STATE"/>
  </segment>
  <segment instanceid="the_burgess_animal_book_for_children_45.txt_74" begin="2692" end="2694">
    <text>be</text>
    <mainVerb begin="2692" end="2694">be</mainVerb>
    <mainReferent begin="2684" end="2686">he</mainReferent>
    <tokens>he must be a Mouse</tokens>
    <annotation annotator="predicted" seType="STATE"/>
  </segment>
  <segment instanceid="the_burgess_animal_book_for_children_45.txt_75" begin="2708" end="2709">
    <text>“</text>
    <mainVerb begin="2708" end="2709">“</mainVerb>
    <tokens>“</tokens>
    <annotation annotator="predicted" seType="IMPERATIVE"/>
  </segment>
  <segment instanceid="the_burgess_animal_book_for_children_45.txt_76" begin="2713" end="2717">
    <text>mean</text>
    <mainVerb begin="2713" end="2717">mean</mainVerb>
    <mainReferent begin="2709" end="2712">You</mainReferent>
    <tokens>You mean Teeny Weeny the Shrew</tokens>
    <annotation annotator="predicted" seType="STATE"/>
  </segment>
  <segment instanceid="the_burgess_animal_book_for_children_45.txt_77" begin="2742" end="2749">
    <text>replied</text>
    <mainVerb begin="2742" end="2749">replied</mainVerb>
    <mainReferent begin="2761" end="2767">Nature</mainReferent>
    <tokens>” replied Old Mother Nature</tokens>
    <annotation annotator="predicted" seType="REPORT"/>
  </segment>
  <segment instanceid="the_burgess_animal_book_for_children_45.txt_78" begin="2769" end="2776">
    <text>smiling</text>
    <mainVerb begin="2769" end="2776">smiling</mainVerb>
    <mainReferent begin="2761" end="2767">Nature</mainReferent>
    <tokens>smiling at Happy Jack</tokens>
    <annotation annotator="predicted" seType="EVENT"/>
  </segment>
  <segment instanceid="the_burgess_animal_book_for_children_45.txt_79" begin="2798" end="2800">
    <text>is</text>
    <mainVerb begin="2798" end="2800">is</mainVerb>
    <mainReferent begin="2794" end="2795">“</mainReferent>
    <tokens>“ He is n't a</tokens>
    <annotation annotator="predicted" seType="STATE"/>
  </segment>
  <segment instanceid="the_burgess_animal_book_for_children_45.txt_80" begin="2817" end="2819">
    <text>is</text>
    <mainVerb begin="2817" end="2819">is</mainVerb>
    <mainReferent begin="2814" end="2816">He</mainReferent>
    <tokens>He is n't even a</tokens>
    <annotation annotator="predicted" seType="STATE"/>
  </segment>
  <segment instanceid="the_burgess_animal_book_for_children_45.txt_81" begin="2845" end="2848">
    <text>try</text>
    <mainVerb begin="2845" end="2848">try</mainVerb>
    <mainReferent begin="2839" end="2840">I</mainReferent>
    <tokens>I 'll try to have him here to-morrow morning</tokens>
    <annotation annotator="predicted" seType="STATE"/>
  </segment>
  <segment instanceid="the_burgess_animal_book_for_children_45.txt_82" begin="2896" end="2899">
    <text>see</text>
    <mainVerb begin="2896" end="2899">see</mainVerb>
    <mainReferent begin="2839" end="2840">I</mainReferent>
    <tokens>we will see</tokens>
    <annotation annotator="predicted" seType="STATE"/>
  </segment>
  <segment instanceid="the_burgess_animal_book_for_children_45.txt_83" begin="2913" end="2917">
    <text>find</text>
    <mainVerb begin="2913" end="2917">find</mainVerb>
    <mainReferent begin="2905" end="2907">we</mainReferent>
    <tokens>what we can find out about him and his relatives . ”</tokens>
    <annotation annotator="predicted" seType="STATE"/>
  </segment>
  <segment instanceid="the_burgess_animal_book_for_children_45.txt_84" begin="3031" end="3036">
    <text>knows</text>
    <mainVerb begin="3031" end="3036">knows</mainVerb>
    <mainReferent begin="3002" end="3003">“</mainReferent>
    <tokens>CHAPTER XIX Teeny Weeny His Cousin “ Of course Old Mother Nature knows</tokens>
    <annotation annotator="predicted" seType="STATE"/>
  </segment>
  <segment instanceid="the_burgess_animal_book_for_children_45.txt_85" begin="3059" end="3061">
    <text>is</text>
    <mainVerb begin="3059" end="3061">is</mainVerb>
    <mainReferent begin="3056" end="3058">it</mainReferent>
    <tokens>it is for me not to believe</tokens>
    <annotation annotator="predicted" seType="STATE"/>
  </segment>
  <segment instanceid="the_burgess_animal_book_for_children_45.txt_86" begin="3107" end="3109">
    <text>is</text>
    <mainVerb begin="3107" end="3109">is</mainVerb>
    <mainReferent begin="3101" end="3106">Weeny</mainReferent>
    <tokens>that Teeny Weeny is a of the Mouse family</tokens>
    <annotation annotator="predicted" seType="STATE"/>
  </segment>
  <segment instanceid="the_burgess_animal_book_for_children_45.txt_87" begin="3142" end="3146">
    <text>said</text>
    <mainVerb begin="3142" end="3146">said</mainVerb>
    <mainReferent begin="2978" end="2983">Weeny</mainReferent>
    <tokens>just the same ” said Happy Jack Squirrel to Peter Rabbit</tokens>
    <annotation annotator="predicted" seType="REPORT"/>
  </segment>
  <segment instanceid="the_burgess_animal_book_for_children_45.txt_88" begin="3193" end="3202">
    <text>scampered</text>
    <mainVerb begin="3193" end="3202">scampered</mainVerb>
    <mainReferent begin="3187" end="3191">they</mainReferent>
    <tokens>as they scampered along to school</tokens>
    <annotation annotator="predicted" seType="EVENT"/>
  </segment>
  <segment instanceid="the_burgess_animal_book_for_children_45.txt_89" begin="3235" end="3238">
    <text>had</text>
    <mainVerb begin="3235" end="3238">had</mainVerb>
    <mainReferent begin="3222" end="3223">I</mainReferent>
    <tokens>“ I never have had a real good look at him</tokens>
    <annotation annotator="predicted" seType="STATE"/>
  </segment>
  <segment instanceid="the_burgess_animal_book_for_children_45.txt_90" begin="3274" end="3277">
    <text>had</text>
    <mainVerb begin="3274" end="3277">had</mainVerb>
    <mainReferent begin="3222" end="3223">I</mainReferent>
    <tokens>I 've had glimpses of him lots of times</tokens>
    <annotation annotator="predicted" seType="STATE"/>
  </segment>
  <segment instanceid="the_burgess_animal_book_for_children_45.txt_91" begin="3320" end="3328">
    <text>supposed</text>
    <mainVerb begin="3320" end="3328">supposed</mainVerb>
    <mainReferent begin="3269" end="3270">I</mainReferent>
    <tokens>I always supposed him a little Mouse with a short tail</tokens>
    <annotation annotator="predicted" seType="GENERALIZING_SENTENCE"/>
  </segment>
  <segment instanceid="the_burgess_animal_book_for_children_45.txt_92" begin="3371" end="3373">
    <text>is</text>
    <mainVerb begin="3371" end="3373">is</mainVerb>
    <mainReferent begin="3368" end="3370">It</mainReferent>
    <tokens>It is to believe ”</tokens>
    <annotation annotator="predicted" seType="STATE"/>
  </segment>
  <segment instanceid="the_burgess_animal_book_for_children_45.txt_93" begin="3399" end="3401">
    <text>is</text>
    <mainVerb begin="3399" end="3401">is</mainVerb>
    <mainReferent begin="3396" end="3398">he</mainReferent>
    <tokens>that he is n't</tokens>
    <annotation annotator="predicted" seType="STATE"/>
  </segment>
  <segment instanceid="the_burgess_animal_book_for_children_45.txt_94" begin="3410" end="3411">
    <text>“</text>
    <mainVerb begin="3410" end="3411">“</mainVerb>
    <tokens>“</tokens>
    <annotation annotator="predicted" seType="IMPERATIVE"/>
  </segment>
  <segment instanceid="the_burgess_animal_book_for_children_45.txt_95" begin="3413" end="3417">
    <text>hope</text>
    <mainVerb begin="3413" end="3417">hope</mainVerb>
    <mainReferent begin="3411" end="3412">I</mainReferent>
    <tokens>I hope</tokens>
    <annotation annotator="predicted" seType="STATE"/>
  </segment>
  <segment instanceid="the_burgess_animal_book_for_children_45.txt_96" begin="3441" end="3444">
    <text>put</text>
    <mainVerb begin="3441" end="3444">put</mainVerb>
    <mainReferent begin="3429" end="3435">Nature</mainReferent>
    <tokens>Old Mother Nature will put him</tokens>
    <annotation annotator="predicted" seType="STATE"/>
  </segment>
  <segment instanceid="the_burgess_animal_book_for_children_45.txt_97" begin="3462" end="3465">
    <text>get</text>
    <mainVerb begin="3462" end="3465">get</mainVerb>
    <mainReferent begin="3455" end="3457">we</mainReferent>
    <tokens>where we can get a good look at him</tokens>
    <annotation annotator="predicted" seType="STATE"/>
  </segment>
  <segment instanceid="the_burgess_animal_book_for_children_45.txt_98" begin="3488" end="3495">
    <text>replied</text>
    <mainVerb begin="3488" end="3495">replied</mainVerb>
    <mainReferent begin="3486" end="3487">”</mainReferent>
    <tokens>” replied Peter</tokens>
    <annotation annotator="predicted" seType="REPORT"/>
  </segment>
  <segment instanceid="the_burgess_animal_book_for_children_45.txt_99" begin="3504" end="3505">
    <text>“</text>
    <mainVerb begin="3504" end="3505">“</mainVerb>
    <tokens>“ Perhaps</tokens>
    <annotation annotator="predicted" seType="IMPERATIVE"/>
  </segment>
  <segment instanceid="the_burgess_animal_book_for_children_45.txt_100" begin="3529" end="3532">
    <text>see</text>
    <mainVerb begin="3529" end="3532">see</mainVerb>
    <mainReferent begin="3518" end="3521">you</mainReferent>
    <tokens>when you really see him</tokens>
    <annotation annotator="predicted" seType="EVENT"/>
  </segment>
  <segment instanceid="the_burgess_animal_book_for_children_45.txt_101" begin="3547" end="3551">
    <text>look</text>
    <mainVerb begin="3547" end="3551">look</mainVerb>
    <mainReferent begin="3529" end="3532">see</mainReferent>
    <tokens>he wo n't look so much like a Mouse . ”</tokens>
    <annotation annotator="predicted" seType="STATE"/>
  </segment>
  <segment instanceid="the_burgess_animal_book_for_children_45.txt_102" begin="3591" end="3598">
    <text>arrived</text>
    <mainVerb begin="3591" end="3598">arrived</mainVerb>
    <mainReferent begin="3583" end="3586">all</mainReferent>
    <tokens>When all had arrived</tokens>
    <annotation annotator="predicted" seType="STATE"/>
  </segment>
  <segment instanceid="the_burgess_animal_book_for_children_45.txt_103" begin="3617" end="3622">
    <text>began</text>
    <mainVerb begin="3617" end="3622">began</mainVerb>
    <mainReferent begin="3610" end="3616">Nature</mainReferent>
    <tokens>Old Mother Nature began the morning lesson at once</tokens>
    <annotation annotator="predicted" seType="EVENT"/>
  </segment>
  <segment instanceid="the_burgess_animal_book_for_children_45.txt_104" begin="3663" end="3670">
    <text>learned</text>
    <mainVerb begin="3663" end="3670">learned</mainVerb>
    <mainReferent begin="3654" end="3657">You</mainReferent>
    <tokens>“ You have learned about all the families in the order of Rodents</tokens>
    <annotation annotator="predicted" seType="STATE"/>
  </segment>
  <segment instanceid="the_burgess_animal_book_for_children_45.txt_105" begin="3721" end="3725">
    <text>said</text>
    <mainVerb begin="3721" end="3725">said</mainVerb>
    <mainReferent begin="3719" end="3720">”</mainReferent>
    <tokens>” said</tokens>
    <annotation annotator="predicted" seType="REPORT"/>
  </segment>
  <segment instanceid="the_burgess_animal_book_for_children_45.txt_106" begin="3731" end="3732">
    <text>“</text>
    <mainVerb begin="3731" end="3732">“</mainVerb>
    <mainReferent begin="3726" end="3729">she</mainReferent>
    <tokens>she “</tokens>
    <annotation annotator="predicted" seType="STATE"/>
  </segment>
  <segment instanceid="the_burgess_animal_book_for_children_45.txt_107" begin="3747" end="3751">
    <text>take</text>
    <mainVerb begin="3747" end="3751">take</mainVerb>
    <mainReferent begin="3739" end="3741">we</mainReferent>
    <tokens>so now we will take up another</tokens>
    <annotation annotator="predicted" seType="STATE"/>
  </segment>
  <segment instanceid="the_burgess_animal_book_for_children_45.txt_108" begin="3787" end="3793">
    <text>called</text>
    <mainVerb begin="3787" end="3793">called</mainVerb>
    <mainReferent begin="3739" end="3741">we</mainReferent>
    <tokens>much smaller order called Insectivora</tokens>
    <annotation annotator="predicted" seType="EVENT"/>
  </segment>
  <segment instanceid="the_burgess_animal_book_for_children_45.txt_109" begin="3810" end="3816">
    <text>wonder</text>
    <mainVerb begin="3810" end="3816">wonder</mainVerb>
    <mainReferent begin="3808" end="3809">I</mainReferent>
    <tokens>I wonder</tokens>
    <annotation annotator="predicted" seType="STATE"/>
  </segment>
  <segment instanceid="the_burgess_animal_book_for_children_45.txt_110" begin="3835" end="3840">
    <text>guess</text>
    <mainVerb begin="3835" end="3840">guess</mainVerb>
    <mainReferent begin="3820" end="3823">any</mainReferent>
    <tokens>if any of you can guess ”</tokens>
    <annotation annotator="predicted" seType="STATE"/>
  </segment>
  <segment instanceid="the_burgess_animal_book_for_children_45.txt_111" begin="3852" end="3857">
    <text>means</text>
    <mainVerb begin="3852" end="3857">means</mainVerb>
    <mainReferent begin="3847" end="3851">that</mainReferent>
    <tokens>what that means</tokens>
    <annotation annotator="predicted" seType="STATE"/>
  </segment>
  <segment instanceid="the_burgess_animal_book_for_children_45.txt_112" begin="3863" end="3864">
    <text>“</text>
    <mainVerb begin="3863" end="3864">“</mainVerb>
    <mainReferent begin="3945" end="3946">”</mainReferent>
    <tokens>“ ”</tokens>
    <annotation annotator="predicted" seType="REPORT"/>
  </segment>
  <segment instanceid="the_burgess_animal_book_for_children_45.txt_113" begin="3867" end="3873">
    <text>sounds</text>
    <mainVerb begin="3867" end="3873">sounds</mainVerb>
    <mainReferent begin="3864" end="3866">It</mainReferent>
    <tokens>It sounds</tokens>
    <annotation annotator="predicted" seType="STATE"/>
  </segment>
  <segment instanceid="the_burgess_animal_book_for_children_45.txt_114" begin="3876" end="3880">
    <text>said</text>
    <mainVerb begin="3876" end="3880">said</mainVerb>
    <mainReferent begin="3863" end="3864">“</mainReferent>
    <tokens>” said Peter Rabbit</tokens>
    <annotation annotator="predicted" seType="REPORT"/>
  </segment>
  <segment instanceid="the_burgess_animal_book_for_children_45.txt_115" begin="3895" end="3896">
    <text>“</text>
    <mainVerb begin="3895" end="3896">“</mainVerb>
    <mainReferent begin="3887" end="3893">Rabbit</mainReferent>
    <tokens>“</tokens>
    <annotation annotator="predicted" seType="STATE"/>
  </segment>
  <segment instanceid="the_burgess_animal_book_for_children_45.txt_116" begin="3910" end="3914">
    <text>have</text>
    <mainVerb begin="3910" end="3914">have</mainVerb>
    <mainReferent begin="3902" end="3904">it</mainReferent>
    <tokens>as if it must have something to do with insects</tokens>
    <annotation annotator="predicted" seType="STATE"/>
  </segment>
  <segment instanceid="the_burgess_animal_book_for_children_45.txt_117" begin="3956" end="3958">
    <text>is</text>
    <mainVerb begin="3956" end="3958">is</mainVerb>
    <mainReferent begin="3950" end="3951">“</mainReferent>
    <tokens>“ That is a very good</tokens>
    <annotation annotator="predicted" seType="STATE"/>
  </segment>
  <segment instanceid="the_burgess_animal_book_for_children_45.txt_118" begin="3986" end="3993">
    <text>replied</text>
    <mainVerb begin="3986" end="3993">replied</mainVerb>
    <mainReferent begin="3984" end="3985">”</mainReferent>
    <tokens>Peter ” replied Old Mother Nature</tokens>
    <annotation annotator="predicted" seType="REPORT"/>
  </segment>
  <segment instanceid="the_burgess_animal_book_for_children_45.txt_119" begin="4014" end="4021">
    <text>smiling</text>
    <mainVerb begin="4014" end="4021">smiling</mainVerb>
    <mainReferent begin="3984" end="3985">”</mainReferent>
    <tokens>smiling at him</tokens>
    <annotation annotator="predicted" seType="EVENT"/>
  </segment>
  <segment instanceid="the_burgess_animal_book_for_children_45.txt_120" begin="4040" end="4044">
    <text>have</text>
    <mainVerb begin="4040" end="4044">have</mainVerb>
    <mainReferent begin="4032" end="4034">It</mainReferent>
    <tokens>“ It does have to do with insects</tokens>
    <annotation annotator="predicted" seType="STATE"/>
  </segment>
  <segment instanceid="the_burgess_animal_book_for_children_45.txt_121" begin="4093" end="4097">
    <text>live</text>
    <mainVerb begin="4093" end="4097">live</mainVerb>
    <mainReferent begin="4070" end="4077">members</mainReferent>
    <tokens>The members of this order live very largely on insects and worms</tokens>
    <annotation annotator="predicted" seType="STATE"/>
  </segment>
  <segment instanceid="the_burgess_animal_book_for_children_45.txt_122" begin="4159" end="4164">
    <text>means</text>
    <mainVerb begin="4159" end="4164">means</mainVerb>
    <mainReferent begin="4070" end="4077">members</mainReferent>
    <tokens>the name Insectivora means insect-eating</tokens>
    <annotation annotator="predicted" seType="STATE"/>
  </segment>
  <segment instanceid="the_burgess_animal_book_for_children_45.txt_123" begin="4187" end="4190">
    <text>are</text>
    <mainVerb begin="4187" end="4190">are</mainVerb>
    <mainReferent begin="4195" end="4203">families</mainReferent>
    <tokens>There are two families in this order , the Shrew family and the Mole family . ”</tokens>
    <annotation annotator="predicted" seType="STATE"/>
  </segment>
</document>
